youtubecomments/__init__.py
youtubecomments-0.1.dist-info/DESCRIPTION.rst
youtubecomments-0.1.dist-info/METADATA
youtubecomments-0.1.dist-info/RECORD
youtubecomments-0.1.dist-info/WHEEL
youtubecomments-0.1.dist-info/metadata.json
youtubecomments-0.1.dist-info/top_level.txt
