Metadata-Version: 2.0
Name: youtubecomments
Version: 0.1
Summary: Get youtube public video comments
Home-page: https://github.com/akash0824/youtubecomments
Author: Akash kumar
Author-email: akashkumar0824@gmail.com
License: UNKNOWN
Keywords: youtube,comments,python,googleapi
Platform: UNKNOWN
